LICENSE
README.md
setup.cfg
setup.py
wacky/__init__.py
wacky/agents/__init__.py
wacky/agents/actor_critic_architectures.py
wacky/agents/base_learner.py
wacky/agents/pre_built/__init__.py
wacky/agents/pre_built/advantage_actor_critic.py
wacky/agents/pre_built/deep_q_network.py
wacky/agents/pre_built/proximal_policy_optimization.py
wacky/agents/pre_built/reinforce.py
wacky/backend/__init__.py
wacky/backend/check_if_exception.py
wacky/backend/exceptions.py
wacky/exploration/__init__.py
wacky/exploration/greedy_epsilon.py
wacky/functional/__init__.py
wacky/functional/base.py
wacky/functional/distributions.py
wacky/functional/funcs.py
wacky/functional/get_optimizer.py
wacky/functional/gym_space_decoder.py
wacky/functional/interpolations.py
wacky/functional/losses.py
wacky/functional/memory.py
wacky/functional/network_constructors.py
wacky/functional/scores.py
wacky/losses/__init__.py
wacky/losses/_base_loss.py
wacky/losses/score_losses.py
wacky/losses/torch_loss_wrapper.py
wacky/memory/__init__.py
wacky/memory/base_memory.py
wacky/memory/experience_replay.py
wacky/memory/prioritized_experience_replay.py
wacky/memory/rollout_buffer.py
wacky/memory/running_mean_std.py
wacky/modules/__init__.py
wacky/modules/_base_module.py
wacky/modules/distribution_networks.py
wacky/modules/noisy_linear.py
wacky/networks/__init__.py
wacky/networks/_base_network.py
wacky/networks/actor_critic_networks.py
wacky/networks/layered_networks.py
wacky/networks/q_networks.py
wacky/optimizer/__init__.py
wacky/optimizer/_base_optimizer.py
wacky/optimizer/torch_optimizer.py
wacky/scores/__init__.py
wacky/scores/return_scores.py
wacky_rl.egg-info/PKG-INFO
wacky_rl.egg-info/SOURCES.txt
wacky_rl.egg-info/dependency_links.txt
wacky_rl.egg-info/requires.txt
wacky_rl.egg-info/top_level.txt